asyncvideoindexer/AsyncVideoIndexer.py
asyncvideoindexer/__init__.py
aio_videoindexer-1.0.0.dev3.dist-info/LICENSE
aio_videoindexer-1.0.0.dev3.dist-info/METADATA
aio_videoindexer-1.0.0.dev3.dist-info/WHEEL
aio_videoindexer-1.0.0.dev3.dist-info/top_level.txt
aio_videoindexer-1.0.0.dev3.dist-info/RECORD
