Metadata-Version: 2.1
Name: aio-videoindexer
Version: 1.0.0.dev3
Summary: An async video indexer package for querying Microsoft Media Services Video Indexer in Python.
Home-page: https://aio-videoindexer.readthedocs.io/en/latest/
Author: Chris Lloyd-Jones
License: MIT
Project-URL: Documentation, https://aio-videoindexer.readthedocs.io/en/latest/
Project-URL: Source, https://github.com/Sealjay-clj/aio-videoindexer
Project-URL: Tracker, https://github.com/Sealjay-clj/aio-videoindexer/issues
Keywords: azure media services video indexer asyncio aio async sdk
Platform: UNKNOWN
Classifier: License :: OSI Approved :: MIT License
Classifier: Programming Language :: Python :: 3
Classifier: Programming Language :: Python :: 3.9
Classifier: Development Status :: 3 - Alpha
Classifier: Intended Audience :: Developers
Classifier: Topic :: Internet :: WWW/HTTP :: Dynamic Content
Classifier: Topic :: Software Development :: Libraries :: Python Modules
Requires-Python: ~=3.6
Requires-Dist: aiohttp
Requires-Dist: aiohttp[speedups]
